{
  "pages-info": {
    "me": {
      "title": "من",
      "description": "وضعیت سلامتی خود را پیگیری کنید."
    },
    "family": {
      "title": "خانواده",
      "description": "وضعیت سلامتی خانواده خود را پیگیری کنید."
    },
    "map": {
      "title": "نقشه",
      "description": "نقشه محیط‌های پر خطر را مشاهده کنید."
    },
    "informing": {
      "title": "آگاهی بخشی",
      "description": "از محتوای آموزشی نرم‌افزار بهره‌مند شوید."
    },
    "places": {
      "title": "محل ها",
      "description": "برای محل‌ها بارکد اختصاصی ایجاد کنید."
    },
    "about-us": {
      "title": "درباره ما",
      "description": ""
    }
  },
  "add-to-home": {
    "android": {
      "title": "نصب نسخه پیشرو ماسک",
      "title1": "کاربر گرامی برای اسفاده  ازنسخه اصلی متناسب با تلفن شما از نسخه اندروید استفاده کنید",

      "step1": {
        "first": "۱- در نوار بالا، روی",
        "end": "کلیک کنید."
      },
      "step2": {
        "add-to-home-screen": "Add To Home screen"
      }
    },
    "ios": {
      "title": "نصب نسخه پیشرو ماسک (مخصوص کاربران iOS)",
      "step1": {
        "first": "۱- در نوار پایین، روی",
        "end": "کلیک کنید."
      }
    },
    "step2": {
      "first": "۲- در منوی باز شده، روی",
      "end": "کلیک کنید."
    },
    "step3": {
      "first": "۳- در آخر، روی Add کلیک کنید."
    },
    "add-later": "بعدا"
  }
}
